AUTHORS
LICENSE
MANIFEST.in
README.rst
setup.py
cmsplugin_facebook_gallery/__init__.py
cmsplugin_facebook_gallery/cms_app.py
cmsplugin_facebook_gallery/cms_plugins.py
cmsplugin_facebook_gallery/models.py
cmsplugin_facebook_gallery/tests.py
cmsplugin_facebook_gallery/views.py
cmsplugin_facebook_gallery/locale/hu/LC_MESSAGES/django.po
django_facebook_gallery.egg-info/PKG-INFO
django_facebook_gallery.egg-info/SOURCES.txt
django_facebook_gallery.egg-info/dependency_links.txt
django_facebook_gallery.egg-info/not-zip-safe
django_facebook_gallery.egg-info/top_level.txt
facebook_gallery/__init__.py
facebook_gallery/admin.py
facebook_gallery/facebook_api.py
facebook_gallery/models.py
facebook_gallery/tests.py
facebook_gallery/urls.py
facebook_gallery/views.py
facebook_gallery/locale/hu/LC_MESSAGES/django.po
facebook_gallery/management/__init__.py
facebook_gallery/management/commands/__init__.py
facebook_gallery/management/commands/fetch_albums.py
facebook_gallery/migrations/0001_initial.py
facebook_gallery/migrations/0002_auto__chg_field_gallery_updated_time__chg_field_gallery_created_time.py
facebook_gallery/migrations/0003_auto__chg_field_image_image__chg_field_image_thumbnail__chg_field_gall.py
facebook_gallery/migrations/0004_auto__chg_field_image_image__chg_field_image_thumbnail__chg_field_gall.py
facebook_gallery/migrations/__init__.py
facebook_gallery/templates/facebook_gallery/fetch_album_form.html
facebook_gallery/templates/facebook_gallery/gallery_detail.html
facebook_gallery/templates/facebook_gallery/gallery_list.html