Metadata-Version: 1.1
Name: django-facebook-gallery
Version: 0.9
Summary: Facebook Gallery for Django
Home-page: https://github.com/nagyv/facebook_gallery
Author: Viktor Nagy
Author-email: viktor.nagy@gmail.com
License: UNKNOWN
Download-URL: https://github.com/nagyv/facebook_gallery/zipball/master
Platform: UNKNOWN
Classifier: Topic :: Internet :: WWW/HTTP :: Dynamic Content
Classifier: Intended Audience :: Developers
Classifier: License :: OSI Approved :: MIT License
Classifier: Programming Language :: Python
Classifier: Programming Language :: Python :: 2.6
Classifier: Programming Language :: Python :: 2.7
Classifier: Framework :: Django
Classifier: Development Status :: 4 - Beta
Classifier: Operating System :: OS Independent
Requires: django(>=1.4)
Requires: facepy
